pycompadre/__init__.py
pycompadre/_pycompadre.cpython-39-darwin.so
pycompadre/libcompadre.dylib
pycompadre/libkokkoscontainers.3.0.0.dylib
pycompadre/libkokkoscontainers.dylib
pycompadre/libkokkoscore.3.0.0.dylib
pycompadre/libkokkoscore.dylib
pycompadre/libkokkoskernels.dylib
pycompadre/examples/pycompadre_example_1d.py
pycompadre/examples/pycompadre_example_2d.py
pycompadre/examples/pycompadre_kernels.py
pycompadre/examples/test_pycompadre.py
pycompadre/examples/test_pycompadre_manifold.py
pycompadre_serial-1.4.5.dist-info/LICENSE.md
pycompadre_serial-1.4.5.dist-info/METADATA
pycompadre_serial-1.4.5.dist-info/WHEEL
pycompadre_serial-1.4.5.dist-info/top_level.txt
pycompadre_serial-1.4.5.dist-info/RECORD
