Metadata-Version: 2.1
Name: pycompadre-serial
Version: 1.4.5
Summary: Compatible Particle Discretization and Remap
Home-page: https://github.com/sandialabs/compadre
Author: Paul Kuberry
Author-email: pkuberry@gmail.com
License: UNKNOWN
Platform: UNKNOWN
Classifier: Programming Language :: Python :: 3
Classifier: License :: OSI Approved :: BSD License
Classifier: Operating System :: Unix
License-File: LICENSE.md
Requires-Dist: numpy
